<?xml version="1.0" encoding="utf-8"?>
<clothing-items>
 <clothing>
  <id>
   897295365
  </id>
  <name>
   Nike Gloves X-7474
  </name>
  <category>
   Gloves
  </category>
  <size>
   M
  </size>
  <color>
   Фиолетовый
  </color>
  <material>
   Хлопок
  </material>
  <price>
   533599
  </price>
  <rating>
   3.46
  </rating>
  <reviews>
   641868
  </reviews>
  <new>
   +
  </new>
  <exclusive>
   yes
  </exclusive>
  <sporty>
   no
  </sporty>
 </clothing>
 <clothing>
  <id>
   540309255
  </id>
  <name>
   DC Sweater H-8781
  </name>
  <category>
   Sweater
  </category>
  <size>
   M
  </size>
  <color>
   Синий
  </color>
  <material>
   Вискоза
  </material>
  <price>
   400823
  </price>
  <rating>
   1.8
  </rating>
  <reviews>
   153174
  </reviews>
  <new>
   +
  </new>
  <sporty>
   yes
  </sporty>
 </clothing>
 <clothing>
  <id>
   637251894
  </id>
  <name>
   PleinSport Handbags M-6806
  </name>
  <category>
   Handbags
  </category>
  <size>
   S
  </size>
  <color>
   Фиолетовый
  </color>
  <material>
   Лен
  </material>
  <price>
   506428
  </price>
  <rating>
   2.23
  </rating>
  <reviews>
   334852
  </reviews>
  <new>
   -
  </new>
  <exclusive>
   no
  </exclusive>
  <sporty>
   yes
  </sporty>
 </clothing>
 <clothing>
  <id>
   388872569
  </id>
  <name>
   Vans Blouse N-6951
  </name>
  <category>
   Blouse
  </category>
  <size>
   XL
  </size>
  <color>
   Голубой
  </color>
  <material>
   Полиэстер
  </material>
  <price>
   459209
  </price>
  <rating>
   1.24
  </rating>
  <reviews>
   414080
  </reviews>
  <new>
   -
  </new>
  <exclusive>
   no
  </exclusive>
 </clothing>
 <clothing>
  <id>
   924695424
  </id>
  <name>
   Puma Belts Z-7450
  </name>
  <category>
   Belts
  </category>
  <size>
   M
  </size>
  <color>
   Синий
  </color>
  <material>
   Кожа
  </material>
  <price>
   977584
  </price>
  <rating>
   3.28
  </rating>
  <reviews>
   210944
  </reviews>
  <new>
   +
  </new>
  <exclusive>
   yes
  </exclusive>
  <sporty>
   no
  </sporty>
 </clothing>
 <clothing>
  <id>
   252154220
  </id>
  <name>
   Adidas T-shirt T-6116
  </name>
  <category>
   T-shirt
  </category>
  <size>
   S
  </size>
  <color>
   Синий
  </color>
  <material>
   Лен
  </material>
  <price>
   230198
  </price>
  <rating>
   2.32
  </rating>
  <reviews>
   815947
  </reviews>
 </clothing>
 <clothing>
  <id>
   215506002
  </id>
  <name>
   Ellesse Shoes N-3736
  </name>
  <category>
   Shoes
  </category>
  <size>
   XL
  </size>
  <color>
   Зеленый
  </color>
  <material>
   Нейлон
  </material>
  <price>
   140439
  </price>
  <rating>
   1.08
  </rating>
  <reviews>
   367016
  </reviews>
  <exclusive>
   no
  </exclusive>
  <sporty>
   no
  </sporty>
 </clothing>
 <clothing>
  <id>
   867986665
  </id>
  <name>
   PleinSport Jeans X-2530
  </name>
  <category>
   Jeans
  </category>
  <size>
   L
  </size>
  <color>
   Синий
  </color>
  <material>
   Шелк
  </material>
  <price>
   454215
  </price>
  <rating>
   4.49
  </rating>
  <reviews>
   573806
  </reviews>
  <new>
   -
  </new>
 </clothing>
 <clothing>
  <id>
   169848721
  </id>
  <name>
   Vans Shirt T-8416
  </name>
  <category>
   Shirt
  </category>
  <size>
   L
  </size>
  <color>
   Фиолетовый
  </color>
  <material>
   Шерсть
  </material>
  <price>
   353953
  </price>
  <rating>
   3.64
  </rating>
  <reviews>
   927245
  </reviews>
  <exclusive>
   yes
  </exclusive>
  <sporty>
   yes
  </sporty>
 </clothing>
 <clothing>
  <id>
   978626568
  </id>
  <name>
   Lacoste T-shirt M-6684
  </name>
  <category>
   T-shirt
  </category>
  <size>
   XXL
  </size>
  <color>
   Оранжевый
  </color>
  <material>
   Нейлон
  </material>
  <price>
   697850
  </price>
  <rating>
   4.39
  </rating>
  <reviews>
   286709
  </reviews>
  <new>
   -
  </new>
  <sporty>
   yes
  </sporty>
 </clothing>
 <clothing>
  <id>
   580448516
  </id>
  <name>
   Converse Handbags P-5604
  </name>
  <category>
   Handbags
  </category>
  <size>
   XL
  </size>
  <color>
   Голубой
  </color>
  <material>
   Шерсть
  </material>
  <price>
   173061
  </price>
  <rating>
   1.31
  </rating>
  <reviews>
   272441
  </reviews>
  <new>
   -
  </new>
  <exclusive>
   no
  </exclusive>
  <sporty>
   no
  </sporty>
 </clothing>
 <clothing>
  <id>
   583215895
  </id>
  <name>
   Converse Jacket I-2433
  </name>
  <category>
   Jacket
  </category>
  <size>
   L
  </size>
  <color>
   Желтый
  </color>
  <material>
   Шелк
  </material>
  <price>
   624821
  </price>
  <rating>
   4.02
  </rating>
  <reviews>
   5782
  </reviews>
  <exclusive>
   no
  </exclusive>
  <sporty>
   no
  </sporty>
 </clothing>
 <clothing>
  <id>
   363824121
  </id>
  <name>
   Brooks T-shirt A-9803
  </name>
  <category>
   T-shirt
  </category>
  <size>
   S
  </size>
  <color>
   Оранжевый
  </color>
  <material>
   Нейлон
  </material>
  <price>
   170962
  </price>
  <rating>
   1.66
  </rating>
  <reviews>
   453157
  </reviews>
 </clothing>
 <clothing>
  <id>
   629774457
  </id>
  <name>
   DC Dress C-3861
  </name>
  <category>
   Dress
  </category>
  <size>
   XXL
  </size>
  <color>
   Синий
  </color>
  <material>
   Шерсть
  </material>
  <price>
   900534
  </price>
  <rating>
   3.64
  </rating>
  <reviews>
   70064
  </reviews>
  <exclusive>
   no
  </exclusive>
  <sporty>
   no
  </sporty>
 </clothing>
 <clothing>
  <id>
   660476544
  </id>
  <name>
   Puma T-shirt V-3581
  </name>
  <category>
   T-shirt
  </category>
  <size>
   M
  </size>
  <color>
   Синий
  </color>
  <material>
   Нейлон
  </material>
  <price>
   467992
  </price>
  <rating>
   3.61
  </rating>
  <reviews>
   168684
  </reviews>
  <sporty>
   yes
  </sporty>
 </clothing>
</clothing-items>
